<?xml version="1.0" encoding="UTF-8" standalone="yes"?>
<externalLink xmlns="http://schemas.openxmlformats.org/spreadsheetml/2006/main" xmlns:mc="http://schemas.openxmlformats.org/markup-compatibility/2006" mc:Ignorable="x14" xmlns:x14="http://schemas.microsoft.com/office/spreadsheetml/2009/9/main"><externalBook xmlns:r="http://schemas.openxmlformats.org/officeDocument/2006/relationships" r:id="rId1"><sheetNames><sheetName val="欢迎关注 @excelhome"/><sheetName val="操作页"/></sheetNames><sheetDataSet><sheetData sheetId="0"/><sheetData sheetId="1"><row r="2"><cell r="A2" t="str"><v>郭靖</v></cell><cell r="B2" t="str"><v>杨贵妃</v></cell></row><row r="3"><cell r="A3" t="str"><v>杨康</v></cell><cell r="B3" t="str"><v>李莲英</v></cell></row><row r="4"><cell r="A4" t="str"><v>东方不败</v></cell><cell r="B4" t="str"><v>梦啸天</v></cell></row><row r="5"><cell r="A5" t="str"><v>穆念慈</v></cell><cell r="B5" t="str"><v>布莱尔</v></cell></row><row r="6"><cell r="A6" t="str"><v>张三丰</v></cell><cell r="B6" t="str"><v>奥巴马</v></cell></row></sheetData></sheetDataSet></externalBook></externalLink>